{
    "version": "2.1.5",
    "description": "Manage your dotfiles across multiple diverse machines, securely.",
    "homepage": "https://chezmoi.io",
    "license": "MIT",
    "architecture": {
        "32bit": {
            "url": "https://github.com/twpayne/chezmoi/releases/download/v2.1.5/chezmoi_2.1.5_windows_i386.zip",
            "hash": "b677f37de3921ac7104dd146061d03fe59c85bbc7545f7a92bab4c1a5538d7fb"
        },
        "64bit": {
            "url": "https://github.com/twpayne/chezmoi/releases/download/v2.1.5/chezmoi_2.1.5_windows_amd64.zip",
            "hash": "d9cb937d3bec23f6b0c70a97dbe013b5888e794f02e1993d986b0bd2cf0f8e1d"
        }
    },
    "bin": "chezmoi.exe",
    "checkver": {
        "github": "https://github.com/twpayne/chezmoi"
    },
    "autoupdate": {
        "architecture": {
            "32bit": {
                "url": "https://github.com/twpayne/chezmoi/releases/download/v$version/chezmoi_$version_windows_i386.zip"
            },
            "64bit": {
                "url": "https://github.com/twpayne/chezmoi/releases/download/v$version/chezmoi_$version_windows_amd64.zip"
            }
        },
        "hash": {
            "url": "$baseurl/chezmoi_$version_checksums.txt"
        }
    }
}
