{
    "version": "1.16.1",
    "description": "Cast media files to UPnP/DLNA Media Renderers and Smart TVs.",
    "homepage": "https://github.com/alexballas/go2tv",
    "license": "MIT",
    "architecture": {
        "64bit": {
            "url": "https://github.com/alexballas/go2tv/releases/download/v1.16.1/go2tv_v1.16.1_windows_amd64.zip",
            "hash": "43871abb192e8655d8869b95b809059ea6e70e72801a81da7a19ad672111a32b"
        }
    },
    "bin": "go2tv.exe",
    "checkver": "github",
    "autoupdate": {
        "architecture": {
            "64bit": {
                "url": "https://github.com/alexballas/go2tv/releases/download/v$version/go2tv_v$version_windows_amd64.zip"
            }
        }
    }
}
